odoo10_addon_contract_sale_generation-10.0.3.0.0-py2.7-nspkg.pth
odoo/addons/contract_sale_generation/README.rst
odoo/addons/contract_sale_generation/__init__.py
odoo/addons/contract_sale_generation/__manifest__.py
odoo/addons/contract_sale_generation/data/contract_cron.xml
odoo/addons/contract_sale_generation/i18n/ca.po
odoo/addons/contract_sale_generation/i18n/de.po
odoo/addons/contract_sale_generation/i18n/el_GR.po
odoo/addons/contract_sale_generation/i18n/es.po
odoo/addons/contract_sale_generation/i18n/es_MX.po
odoo/addons/contract_sale_generation/i18n/fi.po
odoo/addons/contract_sale_generation/i18n/fr.po
odoo/addons/contract_sale_generation/i18n/gl.po
odoo/addons/contract_sale_generation/i18n/hi_IN.po
odoo/addons/contract_sale_generation/i18n/hr.po
odoo/addons/contract_sale_generation/i18n/hr_HR.po
odoo/addons/contract_sale_generation/i18n/hu.po
odoo/addons/contract_sale_generation/i18n/it.po
odoo/addons/contract_sale_generation/i18n/nl.po
odoo/addons/contract_sale_generation/i18n/nl_NL.po
odoo/addons/contract_sale_generation/i18n/pt.po
odoo/addons/contract_sale_generation/i18n/pt_BR.po
odoo/addons/contract_sale_generation/i18n/pt_PT.po
odoo/addons/contract_sale_generation/i18n/ro.po
odoo/addons/contract_sale_generation/i18n/ru.po
odoo/addons/contract_sale_generation/i18n/sk_SK.po
odoo/addons/contract_sale_generation/i18n/sl.po
odoo/addons/contract_sale_generation/i18n/tr.po
odoo/addons/contract_sale_generation/i18n/tr_TR.po
odoo/addons/contract_sale_generation/i18n/zh_CN.po
odoo/addons/contract_sale_generation/models/__init__.py
odoo/addons/contract_sale_generation/models/account_analytic_account.py
odoo/addons/contract_sale_generation/models/account_analytic_contract.py
odoo/addons/contract_sale_generation/tests/__init__.py
odoo/addons/contract_sale_generation/tests/test_contract_sale.py
odoo/addons/contract_sale_generation/views/account_analytic_account_view.xml
odoo10_addon_contract_sale_generation-10.0.3.0.0.dist-info/DESCRIPTION.rst
odoo10_addon_contract_sale_generation-10.0.3.0.0.dist-info/METADATA
odoo10_addon_contract_sale_generation-10.0.3.0.0.dist-info/RECORD
odoo10_addon_contract_sale_generation-10.0.3.0.0.dist-info/WHEEL
odoo10_addon_contract_sale_generation-10.0.3.0.0.dist-info/metadata.json
odoo10_addon_contract_sale_generation-10.0.3.0.0.dist-info/namespace_packages.txt
odoo10_addon_contract_sale_generation-10.0.3.0.0.dist-info/top_level.txt
