Metadata-Version: 2.0
Name: odoo10-addon-contract-sale-generation
Version: 10.0.3.0.0
Summary: Contracts Management - Recurring Sales
Home-page: https://github.com/oca/contract
Author: PESOL, Odoo Community Association (OCA)
Author-email: support@odoo-community.org
License: AGPL-3
Platform: UNKNOWN
Classifier: Programming Language :: Python
Classifier: Framework :: Odoo
Classifier: License :: OSI Approved :: GNU Affero General Public License v3
Requires-Python: ~=2.7
Requires-Dist: odoo (<10.1dev,>=10.0)
Requires-Dist: odoo10-addon-contract
